Metadata-Version: 2.1
Name: minifrpy
Version: 1.2
Summary: langage minimal
Home-page: https://github.com/imenemes/mypylang
Author: imen Lhocine
Author-email: imen.mes@gmail.com
License: MIT
